flask_i18n/__init__.py
flask_i18n/extension.py
flask_i18n-1.1.1.dist-info/LICENSE.md
flask_i18n-1.1.1.dist-info/METADATA
flask_i18n-1.1.1.dist-info/WHEEL
flask_i18n-1.1.1.dist-info/top_level.txt
flask_i18n-1.1.1.dist-info/RECORD
