Metadata-Version: 2.1
Name: flask-i18n
Version: 1.1.1
Summary: Add basic i18n functionality for APIs built as Flask apps. Intended to work in conjuction with Flask-Babel
Home-page: https://github.com/bbelyeu/flask-i18n
Author: Brad Belyeu
Author-email: bradleylamar@gmail.com
License: MIT
Download-URL: https://github.com/bbelyeu/flask-i18n/archive/1.1.1.zip
Keywords: flask,i18n,l10n
Platform: any
Classifier: Environment :: Web Environment
Classifier: Intended Audience :: Developers
Classifier: License :: OSI Approved :: MIT License
Classifier: Operating System :: OS Independent
Classifier: Programming Language :: Python
Classifier: Programming Language :: Python :: 3
Classifier: Topic :: Internet :: WWW/HTTP :: Dynamic Content
Classifier: Topic :: Software Development :: Libraries :: Python Modules
Requires-Dist: Flask
Requires-Dist: Flask-Babel
